agent_management/__init__.py
agent_management/post_requisites/__init__.py
agent_management/post_requisites/config.py
agent_management/post_requisites/handlers.py
agent_management/prerequisites/__init__.py
agent_management/prerequisites/agent_config.py
agent_management/prerequisites/indexing_handler.py
agent_management/providers/__init__.py
agent_management/providers/config.py
agent_management/providers/gemini.py
agent_management/providers/manager.py
agent_management/providers/rovodev.py
agents_new/__init__.py
agents_new/executor.py
agents_new/utils/__init__.py
agents_new/utils/project_context.py
agents_new/utils/system_info.py
baml_client/__init__.py
baml_client/async_client.py
baml_client/config.py
baml_client/globals.py
baml_client/inlinedbaml.py
baml_client/parser.py
baml_client/runtime.py
baml_client/stream_types.py
baml_client/sync_client.py
baml_client/tracing.py
baml_client/type_builder.py
baml_client/type_map.py
baml_client/types.py
baml_src/baml.toml
baml_src/clients.baml
baml_src/types.baml
baml_src/agents/prompts.baml
baml_src/agents/roadmap/prompts.baml
baml_src/agents/roadmap/types.baml
baml_src/agents/roadmap/sections/constraints.baml
baml_src/agents/roadmap/sections/identity.baml
baml_src/agents/roadmap/sections/strategy.baml
baml_src/agents/roadmap/sections/workflow.baml
baml_src/agents/shared/project_context.baml
baml_src/agents/shared/system_info.baml
baml_src/agents/shared/sutra_memory/prompts.baml
baml_src/agents/shared/sutra_memory/types.baml
baml_src/cross_indexing/system_info_cross_indexing.baml
baml_src/cross_indexing/tools.baml
baml_src/cross_indexing/types.baml
baml_src/cross_indexing/code_manager/prompts.baml
baml_src/cross_indexing/code_manager/types.baml
baml_src/cross_indexing/code_manager/sections/base.baml
baml_src/cross_indexing/code_manager/sections/capabilities.baml
baml_src/cross_indexing/code_manager/sections/completion.baml
baml_src/cross_indexing/code_manager/sections/examples.baml
sutrakit-0.1.38.dist-info/licenses/LICENSE
sutrakit-0.1.38.dist-info/METADATA
sutrakit-0.1.38.dist-info/WHEEL
sutrakit-0.1.38.dist-info/entry_points.txt
sutrakit-0.1.38.dist-info/top_level.txt
sutrakit-0.1.38.dist-info/RECORD
