Metadata-Version: 2.4
Name: sutrakit
Version: 0.1.38
Summary: Sutrakit is an AI-powered code manager for coding agents. It spawns agents for multiple projects, connects repos through cross-indexing, and builds dependency graphs for better change suggestions. By automating planning and updates, it helps teams reduce development cost, save time, and improve productivity.
Author: Sutra Graph
License:                     GNU GENERAL PUBLIC LICENSE
Project-URL: Homepage, https://github.com/sutragraph/sutracli
Project-URL: Repository, https://github.com/sutragraph/sutracli
Project-URL: Issues, https://github.com/sutragraph/sutracli/issues
Keywords: ai,cli,code-analysis,code-completion,code-manager,cost-optimization,code-automation,coding-agent,cross-repository-intelligence,roadmap-planning
Classifier: Development Status :: 3 - Alpha
Classifier: Intended Audience :: Developers
Classifier: License :: OSI Approved :: GNU General Public License v3 or later (GPLv3+)
Classifier: Programming Language :: Python :: 3.11
Classifier: Programming Language :: Python :: 3.12
Classifier: Programming Language :: Python :: 3.13
Classifier: Topic :: Software Development :: Libraries :: Python Modules
Classifier: Topic :: Software Development :: Code Generators
Classifier: Topic :: Scientific/Engineering :: Artificial Intelligence
Requires-Python: >=3.11
License-File: LICENSE
Requires-Dist: pydantic==2.11.5
Requires-Dist: loguru==0.7.3
Requires-Dist: onnxruntime==1.22.0
Requires-Dist: numpy==2.2.6
Requires-Dist: tokenizers==0.21.1
Requires-Dist: sqlite-vec==0.1.6
Requires-Dist: pysqlite3-binary==0.5.4
Requires-Dist: requests==2.32.3
Requires-Dist: trafilatura==2.0.0
Requires-Dist: markdownify==1.1.0
Requires-Dist: tree-sitter>=0.25.1
Requires-Dist: tree-sitter-language-pack>=0.9.0
Requires-Dist: setuptools==80.9.0
Requires-Dist: prompt_toolkit==3.0.48
Requires-Dist: rich==14.1.0
Requires-Dist: baml-py==0.210.0
Provides-Extra: dev
Requires-Dist: pre-commit>=3.0.0; extra == "dev"
Dynamic: license-file
